generate_pyproject/__init__.py
generate_pyproject/generate_pyproject.py
ste_test_at-0.2.3.dist-info/METADATA
ste_test_at-0.2.3.dist-info/WHEEL
ste_test_at-0.2.3.dist-info/top_level.txt
ste_test_at-0.2.3.dist-info/RECORD
